comwatt/__init__.py
comwatt-0.12.0.dist-info/LICENSE
comwatt-0.12.0.dist-info/METADATA
comwatt-0.12.0.dist-info/WHEEL
comwatt-0.12.0.dist-info/top_level.txt
comwatt-0.12.0.dist-info/RECORD
