Metadata-Version: 2.1
Name: comwatt
Version: 0.12.0
Summary: Python client for Comwatt
Home-page: https://github.com/51CGO/comwatt
Author: Christophe Godart
Author-email: 51CGO@lilo.org
License: MIT
Keywords: Comwatt,client
License-File: LICENSE
Requires-Dist: selenium
